lensIQ/__init__.py
lensIQ/lensIQ.py
lensiq-1.6.2.dist-info/licenses/LICENSE
lensiq-1.6.2.dist-info/METADATA
lensiq-1.6.2.dist-info/WHEEL
lensiq-1.6.2.dist-info/top_level.txt
lensiq-1.6.2.dist-info/RECORD
