Metadata-Version: 2.4
Name: lensIQ
Version: 1.6.2
Summary: Theia MCR motor control conversions and calculations
Author-email: Mark Peterson <mpeterson@theiatech.com>
Project-URL: Homepage, https://github.com/cliquot22/lensIQ
Project-URL: Bug Tracker, https://github.com/cliquot22/lensIQ/issues
Classifier: Development Status :: 5 - Production/Stable
Classifier: Intended Audience :: Science/Research
Classifier: Intended Audience :: Manufacturing
Classifier: Operating System :: Microsoft :: Windows
Classifier: Programming Language :: Python :: 3
Classifier: Natural Language :: English
Requires-Python: >=3.10
License-File: LICENSE
Requires-Dist: numpy
Requires-Dist: scipy==1.15.2
Dynamic: license-file
